{"cameraMode":{"drawMode":0,"name":"Shaded","section":"Shading Mode"},"sceneLighting":false,"audioPlay":false,"sceneViewState":{"m_AlwaysRefresh":false,"showFog":true,"showSkybox":false,"showFlares":true,"showImageEffects":true,"showParticleSystems":true,"showVisualEffectGraphs":true,"m_FxEnabled":true},"in2DMode":false,"pivot":{"x":-1.0625498294830323,"y":3.429971218109131,"z":17.797142028808595},"rotation":{"x":0.12148795276880264,"y":0.03649991750717163,"z":-0.0038311893586069347,"w":0.9921766519546509},"size":6.079656600952148,"orthographic":false}